setup.cfg
setup.py
stskr_2/stskr_2.py
stskr_2.egg-info/PKG-INFO
stskr_2.egg-info/SOURCES.txt
stskr_2.egg-info/dependency_links.txt
stskr_2.egg-info/not-zip-safe
stskr_2.egg-info/top_level.txt