Metadata-Version: 2.1
Name: stskr-2
Version: 0.0
Summary: stskr_2
Author-email: ilapronin0700@gmail.com
